httpqc/__init__.py
httpqc-0.0.1.dist-info/licenses/LICENSE
httpqc-0.0.1.dist-info/METADATA
httpqc-0.0.1.dist-info/WHEEL
httpqc-0.0.1.dist-info/top_level.txt
httpqc-0.0.1.dist-info/RECORD
