Metadata-Version: 2.4
Name: httpqc
Version: 0.0.1
Summary: HTTP/3 client library using QUIC protocol
Author: Lucas Guerrero
Author-email: nlucas.guerrero@gmail.com
Classifier: Programming Language :: Python :: 3
Classifier: Operating System :: OS Independent
Requires-Python: >=3.7
License-File: LICENSE
Dynamic: author
Dynamic: author-email
Dynamic: classifier
Dynamic: license-file
Dynamic: requires-python
Dynamic: summary
